sdwire.py
sdwirec-0.1.0.dist-info/METADATA
sdwirec-0.1.0.dist-info/WHEEL
sdwirec-0.1.0.dist-info/entry_points.txt
sdwirec-0.1.0.dist-info/RECORD
