Metadata-Version: 2.1
Name: sdwirec
Version: 0.1.0
Summary: Cross platform cli application for Badgerd SDWireC
License: MIT
Author: Talha Can Havadar
Author-email: havadartalha@gmail.com
Requires-Python: >=3.12,<4.0
Classifier: License :: OSI Approved :: MIT License
Classifier: Programming Language :: Python :: 3
Classifier: Programming Language :: Python :: 3.12
Requires-Dist: pyftdi (>=0.55.4,<0.56.0)
Requires-Dist: pyusb (>=1.2.1,<2.0.0)
